tasks/__init__.py
tasks/get_task_history.py
tasks/get_tasks.py
test/__init__.py
test/test_get_task_history.py
test/test_get_tasks.py
taiga-0.1.1.dist-info/METADATA
taiga-0.1.1.dist-info/WHEEL
taiga-0.1.1.dist-info/top_level.txt
taiga-0.1.1.dist-info/RECORD
