Metadata-Version: 2.1
Name: taiga
Version: 0.1.1
Summary: Taiga Library
Author: shikhaverma
